signal_cli_api/__init__.py
signal_cli_api/run_callback.py
signal_cli_api/signal_account.py
signal_cli_api/signal_accounts.py
signal_cli_api/signal_attachment.py
signal_cli_api/signal_call_message.py
signal_cli_api/signal_cli.py
signal_cli_api/signal_common.py
signal_cli_api/signal_contact.py
signal_cli_api/signal_contacts.py
signal_cli_api/signal_device.py
signal_cli_api/signal_devices.py
signal_cli_api/signal_errors.py
signal_cli_api/signal_exceptions.py
signal_cli_api/signal_group.py
signal_cli_api/signal_group_update.py
signal_cli_api/signal_groups.py
signal_cli_api/signal_link_thread.py
signal_cli_api/signal_mention.py
signal_cli_api/signal_mentions.py
signal_cli_api/signal_message.py
signal_cli_api/signal_messages.py
signal_cli_api/signal_preview.py
signal_cli_api/signal_profile.py
signal_cli_api/signal_quote.py
signal_cli_api/signal_reaction.py
signal_cli_api/signal_reactions.py
signal_cli_api/signal_receipt.py
signal_cli_api/signal_receive_thread.py
signal_cli_api/signal_received_message.py
signal_cli_api/signal_recipient.py
signal_cli_api/signal_sent_message.py
signal_cli_api/signal_sticker.py
signal_cli_api/signal_story_message.py
signal_cli_api/signal_sync_message.py
signal_cli_api/signal_text_attachment.py
signal_cli_api/signal_thumbnail.py
signal_cli_api/signal_timestamp.py
signal_cli_api/signal_typing_message.py
SignalCliAPi-0.5.11.5.dist-info/METADATA
SignalCliAPi-0.5.11.5.dist-info/WHEEL
SignalCliAPi-0.5.11.5.dist-info/top_level.txt
SignalCliAPi-0.5.11.5.dist-info/RECORD
