Metadata-Version: 2.1
Name: SignalCliAPi
Version: 0.5.11.5
Summary: A python3 API to the signal-cli application.
Home-page: https://peternearing.ca/signal
Author: Peter Nearing
Author-email: Peter Nearing <me@peternearing.ca>
Project-URL: Bug Tracker, https://github.com/pnearing/SignalCliApi/issues
Classifier: Programming Language :: Python :: 3
Classifier: Operating System :: POSIX :: Linux
Requires-Python: >=3.12
